setup.py
peewe/__init__.py
peewe/cli.py
peewe.egg-info/PKG-INFO
peewe.egg-info/SOURCES.txt
peewe.egg-info/dependency_links.txt
peewe.egg-info/entry_points.txt
peewe.egg-info/top_level.txt